deltamoea/Constants.py
deltamoea/Functions.py
deltamoea/Sampling.py
deltamoea/Sorting.py
deltamoea/Structures.py
deltamoea/__init__.py
deltamoea-1.5.dist-info/METADATA
deltamoea-1.5.dist-info/RECORD
deltamoea-1.5.dist-info/WHEEL
deltamoea-1.5.dist-info/top_level.txt
