Metadata-Version: 2.1
Name: deltamoea
Version: 1.5
Summary: Multi-Objective Grid Search Algorithm
Home-page: https://github.com/DecisionVis/deltamoea
Author: DecisionVis LLC
Author-email: team@decisionvis.com
License: BSD
Keywords: δMOEA,MOEA,grid search,optimization,multi-objective
Platform: UNKNOWN
Classifier: Development Status :: 5 - Production/Stable
Classifier: Intended Audience :: Science/Research
Classifier: Intended Audience :: Developers
Classifier: Topic :: Scientific/Engineering
Classifier: License :: OSI Approved :: BSD License
Classifier: Programming Language :: Python :: 3
Classifier: Programming Language :: Python :: 2.7
